[{"company":"Browsebug","position":"VP Sales","jobLocation":"Monkstown","jobStatus":"declined","jobType":"part-time","createdAt":"2023-08-28T00:35:58Z"},
{"company":"Dabjam","position":"Nurse Practicioner","jobLocation":"Oliveira","jobStatus":"pending","jobType":"internship","createdAt":"2023-08-06T13:54:20Z"},
{"company":"DabZ","position":"Environmental Specialist","jobLocation":"Yangjiang","jobStatus":"interview","jobType":"full-time","createdAt":"2022-12-12T02:18:47Z"},
{"company":"Voomm","position":"Nurse","jobLocation":"Kamionka","jobStatus":"pending","jobType":"part-time","createdAt":"2022-11-01T02:55:26Z"},
{"company":"Skippad","position":"Health Coach III","jobLocation":"Ibaraki","jobStatus":"declined","jobType":"full-time","createdAt":"2022-10-30T11:08:57Z"},
{"company":"Cogilith","position":"Financial Advisor","jobLocation":"Nihaona","jobStatus":"interview","jobType":"internship","createdAt":"2022-10-13T10:17:46Z"},
{"company":"Eare","position":"Senior Financial Analyst","jobLocation":"Gangbei","jobStatus":"declined","jobType":"full-time","createdAt":"2023-08-26T05:28:18Z"},
{"company":"Pixonyx","position":"Paralegal","jobLocation":"Wucheng","jobStatus":"declined","jobType":"full-time","createdAt":"2023-05-21T18:28:15Z"},
{"company":"Rhynoodle","position":"Paralegal","jobLocation":"Kihangara","jobStatus":"pending","jobType":"full-time","createdAt":"2023-06-07T20:36:42Z"},
{"company":"Snaptags","position":"Automation Specialist IV","jobLocation":"Shangdongjie","jobStatus":"interview","jobType":"part-time","createdAt":"2023-04-23T23:06:32Z"},
{"company":"Vinte","position":"Design Engineer","jobLocation":"Douarnenez","jobStatus":"pending","jobType":"internship","createdAt":"2023-01-15T07:29:36Z"},
{"company":"Quamba","position":"Professor","jobLocation":"Xiatuanpu","jobStatus":"declined","jobType":"part-time","createdAt":"2023-09-15T06:19:25Z"},
{"company":"Pixonyx","position":"Project Manager","jobLocation":"Kaga Bandoro","jobStatus":"declined","jobType":"full-time","createdAt":"2023-04-18T11:23:22Z"},
{"company":"Dynazzy","position":"Geological Engineer","jobLocation":"Byumba","jobStatus":"interview","jobType":"full-time","createdAt":"2023-08-14T03:31:28Z"},
{"company":"Oozz","position":"Librarian","jobLocation":"Czarna","jobStatus":"interview","jobType":"full-time","createdAt":"2023-07-03T14:53:35Z"},
{"company":"Chatterpoint","position":"Occupational Therapist","jobLocation":"Vlkoš","jobStatus":"pending","jobType":"internship","createdAt":"2023-05-14T18:57:33Z"},
{"company":"Twitterbeat","position":"Accounting Assistant IV","jobLocation":"Qixia","jobStatus":"pending","jobType":"part-time","createdAt":"2023-03-25T21:29:17Z"},
{"company":"Wikizz","position":"Financial Advisor","jobLocation":"Oeri’u","jobStatus":"interview","jobType":"full-time","createdAt":"2023-06-28T22:52:53Z"},
{"company":"Feedspan","position":"Financial Analyst","jobLocation":"Magallanes","jobStatus":"declined","jobType":"part-time","createdAt":"2023-09-14T12:19:31Z"},
{"company":"Feedbug","position":"Analog Circuit Design manager","jobLocation":"Ipoh","jobStatus":"declined","jobType":"full-time","createdAt":"2022-11-02T00:36:11Z"},
{"company":"Rhyzio","position":"Legal Assistant","jobLocation":"Jiaotang","jobStatus":"pending","jobType":"part-time","createdAt":"2022-11-10T13:24:54Z"},
{"company":"Oyoba","position":"Analyst Programmer","jobLocation":"Tromsø","jobStatus":"declined","jobType":"part-time","createdAt":"2023-01-16T23:04:22Z"},
{"company":"Bluezoom","position":"Human Resources Manager","jobLocation":"Tupsan","jobStatus":"declined","jobType":"internship","createdAt":"2023-02-10T21:53:01Z"},
{"company":"Tagfeed","position":"Health Coach III","jobLocation":"Thap Than","jobStatus":"interview","jobType":"internship","createdAt":"2022-12-20T06:56:15Z"},
{"company":"Twitterworks","position":"Budget/Accounting Analyst III","jobLocation":"Capandanan","jobStatus":"declined","jobType":"part-time","createdAt":"2023-03-22T03:22:06Z"},
{"company":"Browsecat","position":"Senior Quality Engineer","jobLocation":"Araulí","jobStatus":"declined","jobType":"part-time","createdAt":"2023-04-27T12:32:35Z"},
{"company":"Skimia","position":"Electrical Engineer","jobLocation":"Luxor","jobStatus":"pending","jobType":"internship","createdAt":"2023-08-03T05:44:03Z"},
{"company":"Bubbletube","position":"Environmental Specialist","jobLocation":"Gayam","jobStatus":"interview","jobType":"full-time","createdAt":"2023-08-13T04:09:08Z"},
{"company":"Jabbertype","position":"Pharmacist","jobLocation":"Magisterial","jobStatus":"pending","jobType":"internship","createdAt":"2023-03-03T14:57:29Z"},
{"company":"Mita","position":"Chemical Engineer","jobLocation":"Kinalansan","jobStatus":"declined","jobType":"full-time","createdAt":"2023-09-07T15:49:58Z"},
{"company":"Voomm","position":"Electrical Engineer","jobLocation":"Huanan","jobStatus":"pending","jobType":"part-time","createdAt":"2023-09-23T02:25:56Z"},
{"company":"Bluejam","position":"Analyst Programmer","jobLocation":"Cojutepeque","jobStatus":"declined","jobType":"part-time","createdAt":"2023-08-20T03:59:05Z"},
{"company":"Eire","position":"Food Chemist","jobLocation":"Krajan Kulon","jobStatus":"declined","jobType":"internship","createdAt":"2023-04-20T11:12:29Z"},
{"company":"Zoovu","position":"Actuary","jobLocation":"Xiaolin","jobStatus":"declined","jobType":"internship","createdAt":"2023-03-17T18:08:19Z"},
{"company":"Minyx","position":"Pharmacist","jobLocation":"Shaozhai","jobStatus":"pending","jobType":"internship","createdAt":"2023-08-15T02:16:56Z"},
{"company":"Cogidoo","position":"Legal Assistant","jobLocation":"Torino","jobStatus":"declined","jobType":"part-time","createdAt":"2023-08-05T17:00:56Z"},
{"company":"Gabtune","position":"Research Nurse","jobLocation":"Lojigawaran","jobStatus":"interview","jobType":"internship","createdAt":"2023-06-15T06:06:29Z"},
{"company":"Myworks","position":"Financial Advisor","jobLocation":"Xiabeisi","jobStatus":"pending","jobType":"internship","createdAt":"2023-02-18T11:53:14Z"},
{"company":"Oyope","position":"Marketing Assistant","jobLocation":"Međa","jobStatus":"interview","jobType":"part-time","createdAt":"2023-07-16T00:23:17Z"},
{"company":"Twitternation","position":"Marketing Manager","jobLocation":"Sai","jobStatus":"declined","jobType":"part-time","createdAt":"2023-06-09T01:14:32Z"},
{"company":"Skiba","position":"VP Accounting","jobLocation":"Novovarshavka","jobStatus":"pending","jobType":"part-time","createdAt":"2023-06-17T21:21:04Z"},
{"company":"Oozz","position":"Senior Editor","jobLocation":"Potrero Grande","jobStatus":"declined","jobType":"part-time","createdAt":"2023-07-04T20:55:27Z"},
{"company":"Plajo","position":"Financial Advisor","jobLocation":"Carrazeda de Ansiães","jobStatus":"declined","jobType":"part-time","createdAt":"2023-07-22T20:08:57Z"},
{"company":"Digitube","position":"Actuary","jobLocation":"Dobroměřice","jobStatus":"interview","jobType":"part-time","createdAt":"2022-12-03T20:11:40Z"},
{"company":"Skyble","position":"Compensation Analyst","jobLocation":"Saint-Pierre","jobStatus":"declined","jobType":"full-time","createdAt":"2023-01-28T01:11:05Z"},
{"company":"Aivee","position":"Information Systems Manager","jobLocation":"Aral","jobStatus":"interview","jobType":"internship","createdAt":"2023-04-24T08:50:07Z"},
{"company":"Youtags","position":"Environmental Specialist","jobLocation":"Donggou","jobStatus":"declined","jobType":"internship","createdAt":"2023-05-21T13:13:57Z"},
{"company":"Tagchat","position":"Environmental Specialist","jobLocation":"Zelenograd","jobStatus":"interview","jobType":"part-time","createdAt":"2022-10-16T21:23:18Z"},
{"company":"Voolia","position":"Administrative Assistant I","jobLocation":"Pimenta Bueno","jobStatus":"pending","jobType":"internship","createdAt":"2023-04-10T14:33:56Z"},
{"company":"Linkbuzz","position":"Geologist III","jobLocation":"East London","jobStatus":"declined","jobType":"part-time","createdAt":"2023-04-30T18:09:12Z"},
{"company":"Thoughtbeat","position":"Librarian","jobLocation":"Burayevo","jobStatus":"interview","jobType":"internship","createdAt":"2023-05-04T15:48:43Z"},
{"company":"Flashspan","position":"Sales Associate","jobLocation":"Sinargalih","jobStatus":"pending","jobType":"part-time","createdAt":"2023-03-29T02:56:47Z"},
{"company":"Kaymbo","position":"Account Executive","jobLocation":"Qārah","jobStatus":"pending","jobType":"internship","createdAt":"2023-06-06T20:14:20Z"},
{"company":"Twitterlist","position":"Speech Pathologist","jobLocation":"Esigodini","jobStatus":"pending","jobType":"part-time","createdAt":"2023-03-06T14:46:52Z"},
{"company":"Mycat","position":"Structural Engineer","jobLocation":"Castelo","jobStatus":"declined","jobType":"internship","createdAt":"2022-12-01T20:34:48Z"},
{"company":"Avaveo","position":"Research Associate","jobLocation":"Yihe","jobStatus":"pending","jobType":"full-time","createdAt":"2023-02-24T13:09:13Z"},
{"company":"Lazzy","position":"Web Designer II","jobLocation":"Hyrynsalmi","jobStatus":"pending","jobType":"internship","createdAt":"2023-03-10T10:15:01Z"},
{"company":"Flipbug","position":"Human Resources Manager","jobLocation":"Nishiwaki","jobStatus":"declined","jobType":"part-time","createdAt":"2022-10-07T13:28:29Z"},
{"company":"Blogpad","position":"VP Accounting","jobLocation":"Uzdin","jobStatus":"interview","jobType":"part-time","createdAt":"2023-01-13T13:26:56Z"},
{"company":"Jabberbean","position":"Social Worker","jobLocation":"Putrajaya","jobStatus":"interview","jobType":"part-time","createdAt":"2023-06-22T19:01:39Z"},
{"company":"Kwimbee","position":"Junior Executive","jobLocation":"Sungai Iyu","jobStatus":"pending","jobType":"internship","createdAt":"2023-07-11T00:29:58Z"},
{"company":"Youbridge","position":"Administrative Assistant IV","jobLocation":"Wiązownica","jobStatus":"pending","jobType":"part-time","createdAt":"2023-02-07T05:45:17Z"},
{"company":"Yata","position":"Compensation Analyst","jobLocation":"Bologna","jobStatus":"declined","jobType":"full-time","createdAt":"2023-04-10T13:00:18Z"},
{"company":"Devpoint","position":"Web Developer IV","jobLocation":"Tanahwurung","jobStatus":"declined","jobType":"internship","createdAt":"2023-02-01T15:40:41Z"},
{"company":"Buzzshare","position":"Senior Financial Analyst","jobLocation":"Tigbinan","jobStatus":"interview","jobType":"internship","createdAt":"2022-12-27T15:57:25Z"},
{"company":"Zoonder","position":"Business Systems Development Analyst","jobLocation":"Ocampo","jobStatus":"pending","jobType":"internship","createdAt":"2023-05-31T19:53:15Z"},
{"company":"Skyvu","position":"Social Worker","jobLocation":"Makīnsk","jobStatus":"declined","jobType":"internship","createdAt":"2023-07-31T05:14:07Z"},
{"company":"Wikizz","position":"VP Accounting","jobLocation":"Kaliro","jobStatus":"declined","jobType":"internship","createdAt":"2023-01-19T10:23:15Z"},
{"company":"Voolia","position":"Editor","jobLocation":"Lyon","jobStatus":"interview","jobType":"internship","createdAt":"2023-08-30T03:48:36Z"},
{"company":"Meemm","position":"Design Engineer","jobLocation":"Yangjiaping","jobStatus":"declined","jobType":"part-time","createdAt":"2023-07-21T10:30:45Z"},
{"company":"Bubblemix","position":"Cost Accountant","jobLocation":"Kil’mez’","jobStatus":"declined","jobType":"part-time","createdAt":"2022-10-14T12:38:41Z"},
{"company":"Thoughtbridge","position":"Senior Developer","jobLocation":"Bardiyā","jobStatus":"declined","jobType":"part-time","createdAt":"2023-06-17T20:08:13Z"},
{"company":"Tavu","position":"Data Coordinator","jobLocation":"Ibicaraí","jobStatus":"interview","jobType":"part-time","createdAt":"2022-10-26T17:03:49Z"},
{"company":"Meembee","position":"Media Manager I","jobLocation":"Mariscala","jobStatus":"declined","jobType":"part-time","createdAt":"2023-09-18T13:28:19Z"},
{"company":"Feednation","position":"Sales Representative","jobLocation":"Kaduranca","jobStatus":"pending","jobType":"part-time","createdAt":"2023-08-23T14:43:43Z"},
{"company":"Wikizz","position":"Nuclear Power Engineer","jobLocation":"Belyye Stolby","jobStatus":"declined","jobType":"part-time","createdAt":"2023-06-04T11:14:33Z"},
{"company":"Thoughtbeat","position":"Geologist I","jobLocation":"Nanling","jobStatus":"declined","jobType":"full-time","createdAt":"2022-11-16T20:13:33Z"},
{"company":"Vipe","position":"Financial Advisor","jobLocation":"Krasnoarmiys’k","jobStatus":"interview","jobType":"part-time","createdAt":"2023-05-04T13:04:59Z"},
{"company":"Wordpedia","position":"Mechanical Systems Engineer","jobLocation":"Kozakai-chō","jobStatus":"declined","jobType":"full-time","createdAt":"2023-09-07T15:43:58Z"},
{"company":"Miboo","position":"Senior Quality Engineer","jobLocation":"Saint Louis","jobStatus":"interview","jobType":"part-time","createdAt":"2022-12-23T14:46:46Z"},
{"company":"Skyvu","position":"Senior Quality Engineer","jobLocation":"Oro Timur","jobStatus":"declined","jobType":"part-time","createdAt":"2023-01-19T12:44:44Z"},
{"company":"Twinder","position":"Account Representative I","jobLocation":"Xianyang","jobStatus":"interview","jobType":"internship","createdAt":"2023-01-13T12:02:57Z"},
{"company":"Avavee","position":"Account Coordinator","jobLocation":"Maguilling","jobStatus":"declined","jobType":"part-time","createdAt":"2022-10-10T23:15:13Z"},
{"company":"Skipfire","position":"Financial Analyst","jobLocation":"Volzhskiy","jobStatus":"declined","jobType":"internship","createdAt":"2022-10-31T21:04:01Z"},
{"company":"Twitternation","position":"Staff Scientist","jobLocation":"Groznyy","jobStatus":"declined","jobType":"internship","createdAt":"2023-08-06T18:03:42Z"},
{"company":"Voolia","position":"Human Resources Manager","jobLocation":"Ubaté","jobStatus":"interview","jobType":"part-time","createdAt":"2022-10-07T00:36:54Z"},
{"company":"Blogspan","position":"Librarian","jobLocation":"Pionerskiy","jobStatus":"declined","jobType":"part-time","createdAt":"2022-12-02T05:03:16Z"},
{"company":"Thoughtworks","position":"Systems Administrator IV","jobLocation":"Meilin","jobStatus":"declined","jobType":"part-time","createdAt":"2022-10-12T11:02:18Z"},
{"company":"Aimbo","position":"Dental Hygienist","jobLocation":"Kangping","jobStatus":"pending","jobType":"part-time","createdAt":"2023-03-25T01:06:14Z"},
{"company":"Skyba","position":"Physical Therapy Assistant","jobLocation":"Aranđelovac","jobStatus":"pending","jobType":"full-time","createdAt":"2023-02-23T00:42:30Z"},
{"company":"Linktype","position":"Help Desk Operator","jobLocation":"Rudnyy","jobStatus":"interview","jobType":"part-time","createdAt":"2023-09-16T08:30:50Z"},
{"company":"Voolith","position":"Design Engineer","jobLocation":"Karawatu","jobStatus":"interview","jobType":"internship","createdAt":"2023-09-01T12:23:03Z"},
{"company":"Lajo","position":"Programmer III","jobLocation":"Zaliznychne","jobStatus":"pending","jobType":"full-time","createdAt":"2023-02-08T19:50:18Z"},
{"company":"Digitube","position":"Pharmacist","jobLocation":"Razan","jobStatus":"declined","jobType":"part-time","createdAt":"2022-10-11T16:55:58Z"},
{"company":"Centidel","position":"Senior Sales Associate","jobLocation":"Goyang-si","jobStatus":"pending","jobType":"part-time","createdAt":"2023-02-08T11:39:05Z"},
{"company":"Yakidoo","position":"Registered Nurse","jobLocation":"Xishan","jobStatus":"pending","jobType":"internship","createdAt":"2022-11-09T22:52:12Z"},
{"company":"Mynte","position":"Senior Cost Accountant","jobLocation":"Cibalung","jobStatus":"interview","jobType":"part-time","createdAt":"2023-05-28T03:33:29Z"},
{"company":"Wordware","position":"Environmental Tech","jobLocation":"Gamay","jobStatus":"interview","jobType":"part-time","createdAt":"2023-04-16T16:57:25Z"},
{"company":"Kanoodle","position":"Structural Analysis Engineer","jobLocation":"Kosakowo","jobStatus":"declined","jobType":"part-time","createdAt":"2023-04-04T11:50:05Z"},
{"company":"Kare","position":"Environmental Specialist","jobLocation":"Grimshaw","jobStatus":"declined","jobType":"part-time","createdAt":"2023-06-12T09:53:25Z"}]